mdsanima/__init__.py
mdsanima/animation.py
mdsanima/render.py
mdsanima-0.1.1.dist-info/LICENSE
mdsanima-0.1.1.dist-info/METADATA
mdsanima-0.1.1.dist-info/WHEEL
mdsanima-0.1.1.dist-info/top_level.txt
mdsanima-0.1.1.dist-info/RECORD
