Metadata-Version: 2.1
Name: mdsanima
Version: 0.1.1
Summary: The package contains modules that will help in calculating rendering time.
Home-page: https://github.com/mdsanima/mdsanima
Author: Marcin Rozewski
Author-email: marcinrozewski@gmail.com
License: MIT License
Keywords: mdsanima,render time,calculator render time,blender,blener3d,rendering,houdini,sidefx,vfx,cinema4d,cycles,redshift,render engine,octane render,mantra,vray,clarisse ifx
Platform: UNKNOWN
Classifier: Development Status :: 5 - Production/Stable
Classifier: Intended Audience :: Developers
Classifier: License :: OSI Approved :: MIT License
Classifier: Natural Language :: English
Classifier: Programming Language :: Python :: 3
Classifier: Programming Language :: Python :: 3.5
Classifier: Programming Language :: Python :: 3.6
Classifier: Programming Language :: Python :: 3.7
Requires-Python: >=3.6
Requires-Dist: humanfriendly
Provides-Extra: docs
Requires-Dist: sphinx ; extra == 'docs'
Requires-Dist: sphinx-autoapi ; extra == 'docs'
Requires-Dist: sphinx-rtd-theme ; extra == 'docs'
Requires-Dist: sphinx-bootstrap-theme ; extra == 'docs'
Requires-Dist: sphinx-prompt ; extra == 'docs'
Requires-Dist: sphinx-tabs ; extra == 'docs'
Requires-Dist: recommonmark ; extra == 'docs'
